setup.py
type_config/__init__.py
type_config/errors.py
type_config-1.3.0.dist-info/LICENSE
type_config-1.3.0.dist-info/METADATA
type_config-1.3.0.dist-info/WHEEL
type_config-1.3.0.dist-info/top_level.txt
type_config-1.3.0.dist-info/RECORD
