Metadata-Version: 2.1
Name: type-config
Version: 1.3.0
Summary: A small library that adds types and auto-validation to your config files!
Author-email: Biosa Alex <mochittodeveloper@gmail.com>
Project-URL: Homepage, https://github.com/Mochitto/type-config
Project-URL: Bug Tracker, https://github.com/Mochitto/type-config/issues
Classifier: Programming Language :: Python :: 3
Classifier: License :: OSI Approved :: MIT License
Classifier: Operating System :: OS Independent
Classifier: Development Status :: 3 - Alpha
Classifier: Intended Audience :: Developers
Classifier: Natural Language :: English
Classifier: Topic :: Software Development :: Libraries
Classifier: Topic :: Utilities
Requires-Python: >=3.10
License-File: LICENSE
